pyconlai/__init__.py
pyconlai/context.py
pyconlai/datasets/README.md
pyconlai/datasets/__init__.py
pyconlai/datasets/classification.py
pyconlai/datasets/mixin.py
pyconlai/optimizer/__init__.py
pyconlai/optimizer/dsgd.py
pyconlai/optimizer/lscaffold.py
pyconlai/optimizer/mixin.py
pyconlai/pb/README.md
pyconlai/pb/__init__.py
pyconlai/pb/conl.proto
pyconlai/pb/conl_pb2.py
pyconlai-0.1.4.dist-info/METADATA
pyconlai-0.1.4.dist-info/WHEEL
pyconlai-0.1.4.dist-info/licenses/LICENSE
pyconlai-0.1.4.dist-info/RECORD
