Metadata-Version: 2.4
Name: pyconlai
Version: 0.1.4
Summary: Client optimizer for use with ConLAi which is ledger type federated learning framework
Author: Rosso inc
License-File: LICENSE
Requires-Python: >=3.10
Requires-Dist: fastapi
Requires-Dist: numpy
Requires-Dist: omegaconf
Requires-Dist: protobuf
Requires-Dist: pydantic
Requires-Dist: pyyaml
Requires-Dist: requests
Requires-Dist: torch
Requires-Dist: torchvision
Requires-Dist: uvicorn[standard]
Requires-Dist: websocket-client
